stempeg/__init__.py
stempeg/cli.py
stempeg/cmds.py
stempeg/read.py
stempeg/write.py
stempeg/data/The Easton Ellises - Falcon 69.stem.mp4
stempeg/data/default_metadata.json
stempeg-0.2.4.dist-info/licenses/LICENSE
stempeg-0.2.4.dist-info/METADATA
stempeg-0.2.4.dist-info/WHEEL
stempeg-0.2.4.dist-info/entry_points.txt
stempeg-0.2.4.dist-info/top_level.txt
stempeg-0.2.4.dist-info/zip-safe
stempeg-0.2.4.dist-info/RECORD
