Metadata-Version: 2.4
Name: stempeg
Version: 0.2.4
Summary: Read and write stem/multistream audio files
Home-page: http://github.com/faroit/stempeg
Author: Fabian-Robert Stoeter
Author-email: mail@faroit.com
Project-URL: Bug Reports, https://github.com/faroit/stempeg/issues
Keywords: stems audio reader
Classifier: Development Status :: 4 - Beta
Classifier: Environment :: Console
Classifier: Intended Audience :: Telecommunications Industry
Classifier: Intended Audience :: Science/Research
Classifier: Programming Language :: Python :: 3.9
Classifier: Programming Language :: Python :: 3.10
Classifier: Programming Language :: Python :: 3.11
Classifier: Topic :: Multimedia :: Sound/Audio :: Analysis
Classifier: Topic :: Multimedia :: Sound/Audio :: Sound Synthesis
License-File: LICENSE
Requires-Dist: numpy>=1.6
Requires-Dist: ffmpeg-python>=0.2.0
Provides-Extra: tests
Requires-Dist: pytest; extra == "tests"
Dynamic: author
Dynamic: author-email
Dynamic: classifier
Dynamic: description
Dynamic: description-content-type
Dynamic: home-page
Dynamic: keywords
Dynamic: license-file
Dynamic: project-url
Dynamic: provides-extra
Dynamic: requires-dist
Dynamic: summary
